llm_context_generator/__init__.py
llm_context_generator/cli.py
llm_context_generator/core.py
llm_context_generator-1.0.0.dist-info/LICENSE.txt
llm_context_generator-1.0.0.dist-info/METADATA
llm_context_generator-1.0.0.dist-info/WHEEL
llm_context_generator-1.0.0.dist-info/entry_points.txt
llm_context_generator-1.0.0.dist-info/RECORD
