Metadata-Version: 2.1
Name: llm-context-generator
Version: 1.0.0
Summary: LLM context generator
Home-page: https://github.com/jeanpimentel/llm-context
License: MIT
Author: Jean Pimentel
Author-email: contato@jeanpimentel.com.br
Requires-Python: >=3.9,<3.13
Classifier: Development Status :: 3 - Alpha
Classifier: Environment :: Console
Classifier: Intended Audience :: Developers
Classifier: License :: OSI Approved :: MIT License
Classifier: Programming Language :: Python :: 3
Classifier: Programming Language :: Python :: 3.9
Classifier: Programming Language :: Python :: 3.10
Classifier: Programming Language :: Python :: 3.11
Classifier: Programming Language :: Python :: 3.12
Classifier: Topic :: Software Development
Classifier: Topic :: Utilities
Requires-Dist: click (==8.1.7)
Requires-Dist: pathspec (==0.12.1)
Project-URL: Repository, https://github.com/jeanpimentel/llm-context
